README.md
setup.py
eternalswarm.mind.egg-info/PKG-INFO
eternalswarm.mind.egg-info/SOURCES.txt
eternalswarm.mind.egg-info/dependency_links.txt
eternalswarm.mind.egg-info/namespace_packages.txt
eternalswarm.mind.egg-info/not-zip-safe
eternalswarm.mind.egg-info/requires.txt
eternalswarm.mind.egg-info/top_level.txt
eternalswarm/mind/__init__.py
eternalswarm/mind/__init__.pyi
eternalswarm/mind/bloodhound_pb2.py
eternalswarm/mind/bloodhound_pb2.pyi
eternalswarm/mind/bloodhound_pb2_grpc.py
eternalswarm/mind/callback_pb2.py
eternalswarm/mind/callback_pb2.pyi
eternalswarm/mind/callback_pb2_grpc.py
eternalswarm/mind/client.py
eternalswarm/mind/cracker_pb2.py
eternalswarm/mind/cracker_pb2.pyi
eternalswarm/mind/cracker_pb2_grpc.py
eternalswarm/mind/exploitation_pb2.py
eternalswarm/mind/exploitation_pb2.pyi
eternalswarm/mind/exploitation_pb2_grpc.py
eternalswarm/mind/information_pb2.py
eternalswarm/mind/information_pb2.pyi
eternalswarm/mind/information_pb2_grpc.py
eternalswarm/mind/metasploit_pb2.py
eternalswarm/mind/metasploit_pb2.pyi
eternalswarm/mind/metasploit_pb2_grpc.py
eternalswarm/mind/models_pb2.py
eternalswarm/mind/models_pb2.pyi
eternalswarm/mind/models_pb2_grpc.py
eternalswarm/mind/py.typed
eternalswarm/mind/relaying_pb2.py
eternalswarm/mind/relaying_pb2.pyi
eternalswarm/mind/relaying_pb2_grpc.py
eternalswarm/mind/scanner_pb2.py
eternalswarm/mind/scanner_pb2.pyi
eternalswarm/mind/scanner_pb2_grpc.py
eternalswarm/mind/terminal_pb2.py
eternalswarm/mind/terminal_pb2.pyi
eternalswarm/mind/terminal_pb2_grpc.py
eternalswarm/mind/wireguard_pb2.py
eternalswarm/mind/wireguard_pb2.pyi
eternalswarm/mind/wireguard_pb2_grpc.py