Metadata-Version: 2.1
Name: eternalswarm.mind
Version: 0.2.8
Summary: The protobuf files to talk to the eternalswarm drone.
Home-page: https://gitlab.com/eternal-swarm/mind
Author: Matthijs Gielen
Author-email: eternalswarm@mwgielen.com
License: UNKNOWN
Platform: UNKNOWN
Classifier: Development Status :: 3 - Alpha
Classifier: Programming Language :: Python :: 3.6
Classifier: Programming Language :: Python :: 3.7
Classifier: Programming Language :: Python :: 3.8
Classifier: Intended Audience :: Information Technology
Classifier: Typing :: Typed
Requires-Python: >=3.6
Provides-Extra: dev
